joeldata/__init__.py
joeldata/queue.py
joeldata/stack.py
joeldata/BST/BinarySearchTree.py
joeldata/BST/TreeNode.py
joeldata/BST/__init__.py
joeldata/HashTable/HashTable.py
joeldata/HashTable/__init__.py
joeldata/HashTable/hash.py
joeldata-1.0.5.dist-info/LICENSE
joeldata-1.0.5.dist-info/METADATA
joeldata-1.0.5.dist-info/WHEEL
joeldata-1.0.5.dist-info/top_level.txt
joeldata-1.0.5.dist-info/RECORD
