Metadata-Version: 2.1
Name: joeldata
Version: 1.0.5
Author-email: Joel Grayson <joel@joelgrayson.com>
License: MIT License        
Project-URL: Homepage, https://github.com/JoelGrayson/JoelData
Project-URL: Bug Tracker, https://github.com/JoelGrayson/JoelData/issues
Classifier: Programming Language :: Python :: 3
Classifier: License :: OSI Approved :: MIT License
Classifier: Operating System :: OS Independent
Requires-Python: >=3.7
License-File: LICENSE
